ProsperTestUtils-1.0.0.dist-info/METADATA
ProsperTestUtils-1.0.0.dist-info/RECORD
ProsperTestUtils-1.0.0.dist-info/WHEEL
ProsperTestUtils-1.0.0.dist-info/entry_points.txt
ProsperTestUtils-1.0.0.dist-info/top_level.txt
prosper/test_utils/__init__.py
prosper/test_utils/_version.py
prosper/test_utils/app.cfg
prosper/test_utils/config_utils.py
prosper/test_utils/docker_utils.py
prosper/test_utils/exceptions.py
prosper/test_utils/root_schema.schema
prosper/test_utils/schema_utils.py
prosper/test_utils/version.txt
