Metadata-Version: 2.1
Name: ProsperTestUtils
Version: 1.0.0
Summary: Test helpers for Prosper projects
Home-page: https://github.com/EVEprosper/ProsperTestUtils
Author: John Purcell
Author-email: prospermarketshow@gmail.com
License: Unlicense
Keywords: testing docker configuration-management pytest
Platform: UNKNOWN
Classifier: Programming Language :: Python :: 3.5
Classifier: Programming Language :: Python :: 3.6
Classifier: Operating System :: POSIX
Classifier: Operating System :: Microsoft :: Windows
Classifier: Operating System :: MacOS :: MacOS X
Classifier: Topic :: Software Development :: Testing
Classifier: Topic :: Software Development :: Libraries
Classifier: Topic :: Utilities
Classifier: Intended Audience :: Developers
Classifier: License :: Public Domain
Requires-Python: >=3.5
Provides-Extra: dev
Requires-Dist: prospercommon
Requires-Dist: requests
Requires-Dist: semantic-version
Requires-Dist: plumbum
Requires-Dist: docker
Requires-Dist: deepdiff
Requires-Dist: jsonschema
Requires-Dist: genson
Requires-Dist: pymongo
Requires-Dist: dnspython
Provides-Extra: dev
Requires-Dist: sphinx; extra == 'dev'
Requires-Dist: sphinxcontrib-napoleon; extra == 'dev'
